{
  "value": 1.258,
  "valuePerYear": {
    "2555": 1.254,
    "2556": 1.274,
    "2557": 1.274,
    "2558": 1.304,
    "2559": 1.296,
    "2560": 1.344,
    "2561": 1.344,
    "2562": 1.374,
    "2563": 1.323,
    "2564": 1.707,
    "2565": 1.332,
    "2566": 1.258
  },
  "minimumPoint": {
    "districtId": 11,
    "districtName": "ทวีวัฒนา",
    "year": 2564,
    "value": 0.642
  },
  "maximumPoint": {
    "districtId": 17,
    "districtName": "บางขุนเทียน",
    "year": 2564,
    "value": 3.578
  },
  "budgetPerYear": {
    "2555": {
      "all": 5341762100,
      "focused": 1285179400
    },
    "2556": {
      "all": 5628543100,
      "focused": 1407871200
    },
    "2557": {
      "all": 6014678700,
      "focused": 1429154200
    },
    "2558": {
      "all": 5795749100,
      "focused": 1428721400
    },
    "2559": {
      "all": 5715356700,
      "focused": 1487580000
    },
    "2560": {
      "all": 5977032600,
      "focused": 1480766400
    },
    "2561": {
      "all": 5841390560,
      "focused": 1572957400
    },
    "2562": {
      "all": 5980481300,
      "focused": 1638093800
    },
    "2563": {
      "all": 6443658340,
      "focused": 1663339900
    },
    "2564": {
      "all": 6182171000,
      "focused": 1638751730
    },
    "2565": {
      "all": 5291407258,
      "focused": 797747639
    },
    "2566": {
      "all": 6071269991,
      "focused": 175446760
    }
  },
  "budgetOverall": {
    "all": 70283500749,
    "focused": 16005609829
  },
  "rankings": [
    {
      "ranked": 1,
      "districtId": 23,
      "districtName": "บางบอน",
      "value": 1.855
    },
    {
      "ranked": 2,
      "districtId": 17,
      "districtName": "บางขุนเทียน",
      "value": 1.578
    },
    {
      "ranked": 3,
      "districtId": 38,
      "districtName": "ลาดกระบัง",
      "value": 1.54
    },
    {
      "ranked": 4,
      "districtId": 11,
      "districtName": "ทวีวัฒนา",
      "value": 1.485
    },
    {
      "ranked": 5,
      "districtId": 10,
      "districtName": "ตลิ่งชัน",
      "value": 1.391
    },
    {
      "ranked": 6,
      "districtId": 20,
      "districtName": "บางแค",
      "value": 1.311
    },
    {
      "ranked": 7,
      "districtId": 33,
      "districtName": "ภาษีเจริญ",
      "value": 1.23
    },
    {
      "ranked": 8,
      "districtId": 37,
      "districtName": "ราษฎร์บูรณะ",
      "value": 1.192
    },
    {
      "ranked": 9,
      "districtId": 34,
      "districtName": "มีนบุรี",
      "value": 1.183
    },
    {
      "ranked": 10,
      "districtId": 6,
      "districtName": "จอมทอง",
      "value": 1.156
    },
    {
      "ranked": 11,
      "districtId": 12,
      "districtName": "ทุ่งครุ",
      "value": 1.046
    },
    {
      "ranked": 12,
      "districtId": 3,
      "districtName": "คลองสามวา",
      "value": 1.004
    },
    {
      "ranked": 13,
      "districtId": 47,
      "districtName": "หนองแขม",
      "value": 0.861
    },
    {
      "ranked": 14,
      "districtId": 48,
      "districtName": "หนองจอก",
      "value": 0.777
    }
  ],
  "benchmarks": [
    {
      "zoneId": "all",
      "areaName": "ทุกเขตในกรุงเทพมหานคร",
      "value": 1.82
    },
    {
      "zoneId": "residence",
      "areaName": "ทุกเขตพื้นที่อยู่อาศัย",
      "value": 1.437
    },
    {
      "zoneId": "suburban",
      "areaName": "ทุกเขตพื้นที่อยู่อาศัยชานเมือง",
      "value": 1.258
    },
    {
      "zoneId": "tourism-and-cultural",
      "areaName": "พื้นที่อนุรักษ์ศิลปวัฒนธรรมและส่งเสริมการท่องเที่ยว",
      "value": 2.166
    },
    {
      "zoneId": "business",
      "areaName": "พื้นที่ศูนย์กลางธุรกิจและพาณิชยกรรม",
      "value": 2.599
    }
  ]
}