{
  "value": 7.64,
  "valuePerYear": {
    "2555": 4.42,
    "2556": 4.57,
    "2557": 5.03,
    "2558": 5.18,
    "2559": 5.59,
    "2560": 5.76,
    "2561": 5.76,
    "2562": 6.34,
    "2563": 10.14,
    "2564": 10.71,
    "2565": 7.05,
    "2566": 7.64
  },
  "minimumPoint": {
    "districtId": 41,
    "districtName": "วัฒนา",
    "year": 2555,
    "value": 1.03
  },
  "maximumPoint": {
    "districtId": 27,
    "districtName": "ปทุมวัน",
    "year": 2564,
    "value": 26.4
  },
  "budgetPerYear": {
    "2555": {
      "all": 3956402600,
      "focused": 194551100
    },
    "2556": {
      "all": 4164147400,
      "focused": 215977200
    },
    "2557": {
      "all": 4164147400,
      "focused": 215977200
    },
    "2558": {
      "all": 4131289700,
      "focused": 229544300
    },
    "2559": {
      "all": 4159547700,
      "focused": 187846100
    },
    "2560": {
      "all": 4356943900,
      "focused": 169905800
    },
    "2561": {
      "all": 4305063920,
      "focused": 180688600
    },
    "2562": {
      "all": 4432998700,
      "focused": 272717100
    },
    "2563": {
      "all": 4523127314,
      "focused": 271206200
    },
    "2564": {
      "all": 4725704700,
      "focused": 257825500
    },
    "2565": {
      "all": 3944054490,
      "focused": 260155594
    },
    "2566": {
      "all": 4398523678,
      "focused": 91801500
    }
  },
  "budgetOverall": {
    "all": 51261951502,
    "focused": 2548196194
  },
  "rankings": [
    {
      "ranked": 1,
      "districtId": 27,
      "districtName": "ปทุมวัน",
      "value": 23.98
    },
    {
      "ranked": 2,
      "districtId": 1,
      "districtName": "คลองเตย",
      "value": 14.11
    },
    {
      "ranked": 3,
      "districtId": 5,
      "districtName": "จตุจักร",
      "value": 14.06
    },
    {
      "ranked": 4,
      "districtId": 36,
      "districtName": "ราชเทวี",
      "value": 10.85
    },
    {
      "ranked": 5,
      "districtId": 35,
      "districtName": "ยานนาวา",
      "value": 7.53
    },
    {
      "ranked": 6,
      "districtId": 50,
      "districtName": "ห้วยขวาง",
      "value": 5.53
    },
    {
      "ranked": 7,
      "districtId": 45,
      "districtName": "สาทร",
      "value": 5.09
    },
    {
      "ranked": 8,
      "districtId": 19,
      "districtName": "บางคอแหลม",
      "value": 4.54
    },
    {
      "ranked": 9,
      "districtId": 25,
      "districtName": "บางรัก",
      "value": 3.97
    },
    {
      "ranked": 10,
      "districtId": 30,
      "districtName": "พญาไท",
      "value": 3.22
    },
    {
      "ranked": 11,
      "districtId": 21,
      "districtName": "บางซื่อ",
      "value": 2.39
    },
    {
      "ranked": 12,
      "districtId": 41,
      "districtName": "วัฒนา",
      "value": 2.02
    },
    {
      "ranked": 13,
      "districtId": 8,
      "districtName": "ดินแดง",
      "value": 1.99
    }
  ],
  "benchmarks": [
    {
      "zoneId": "all",
      "areaName": "ทุกเขตในกรุงเทพมหานคร",
      "value": 7.87
    },
    {
      "zoneId": "residence",
      "areaName": "ทุกเขตพื้นที่อยู่อาศัย",
      "value": 9.02
    },
    {
      "zoneId": "suburban",
      "areaName": "ทุกเขตพื้นที่อยู่อาศัยชานเมือง",
      "value": 8.47
    },
    {
      "zoneId": "tourism-and-cultural",
      "areaName": "พื้นที่อนุรักษ์ศิลปวัฒนธรรมและส่งเสริมการท่องเที่ยว",
      "value": 6.91
    },
    {
      "zoneId": "business",
      "areaName": "พื้นที่ศูนย์กลางธุรกิจและพาณิชยกรรม",
      "value": 7.64
    }
  ],
  "publicGreenSpacePerCapita": null
}