{
  "value": 5,
  "valuePerYear": {
    "2555": 68,
    "2556": 88,
    "2557": 358,
    "2558": 44,
    "2559": 16,
    "2560": 57,
    "2561": 54,
    "2562": 139,
    "2563": 10,
    "2564": 11,
    "2565": 6,
    "2566": 5
  },
  "minimumPoint": {
    "value": 5,
    "year": 2566,
    "districtId": 5,
    "districtName": "จตุจักร"
  },
  "maximumPoint": {
    "value": 358,
    "year": 2557,
    "districtId": 5,
    "districtName": "จตุจักร"
  },
  "budgetPerYear": {
    "2555": {
      "all": 457222000,
      "focused": 12914300
    },
    "2556": {
      "all": 539599200,
      "focused": 13652900
    },
    "2557": {
      "all": 539599200,
      "focused": 13652900
    },
    "2558": {
      "all": 545380000,
      "focused": 14948700
    },
    "2559": {
      "all": 500367500,
      "focused": 15678300
    },
    "2560": {
      "all": 534968000,
      "focused": 16753400
    },
    "2561": {
      "all": 502145840,
      "focused": 17695200
    },
    "2562": {
      "all": 540198000,
      "focused": 26869900
    },
    "2563": {
      "all": 534717800,
      "focused": 14512000
    },
    "2564": {
      "all": 539155000,
      "focused": 20479700
    },
    "2565": {
      "all": 485626190,
      "focused": 19398000
    },
    "2566": {
      "all": 511457900,
      "focused": 9525800
    }
  },
  "budgetOverall": {
    "all": 6230436630,
    "focused": 196081100
  },
  "ranked": 7,
  "rankings": [
    {
      "ranked": 3,
      "year": 2555,
      "value": 68
    },
    {
      "ranked": 1,
      "year": 2556,
      "value": 88
    },
    {
      "ranked": 1,
      "year": 2557,
      "value": 358
    },
    {
      "ranked": 8,
      "year": 2558,
      "value": 44
    },
    {
      "ranked": 9,
      "year": 2559,
      "value": 16
    },
    {
      "ranked": 8,
      "year": 2560,
      "value": 57
    },
    {
      "ranked": 4,
      "year": 2561,
      "value": 54
    },
    {
      "ranked": 1,
      "year": 2562,
      "value": 139
    },
    {
      "ranked": 6,
      "year": 2563,
      "value": 10
    },
    {
      "ranked": 5,
      "year": 2564,
      "value": 11
    },
    {
      "ranked": 10,
      "year": 2565,
      "value": 6
    },
    {
      "ranked": 7,
      "year": 2566,
      "value": 5
    }
  ],
  "floodHotspots": [
    {
      "name": "ถนนกำแพงเพชร 2",
      "description": "หน้าหมอชิตใหม่"
    },
    {
      "name": "ถนนรัชดาภิเษก",
      "description": "หน้าธนาคารกรุงเทพ"
    },
    {
      "name": "ถนนเทศบาลสงเคราะห์",
      "description": "ตลาดประชานิเวศน์"
    },
    {
      "name": "ถนนรัชดาภิเษก",
      "description": "ซอยรัชดา 32 ธนาคารกรุงเทพ"
    },
    {
      "name": "ถนนรัชดาภิเษก",
      "description": "ศาลอาญารัชดา"
    },
    {
      "name": "ถนนรัชดาภิเษก",
      "description": "แยกรัชโยธินถึงแยกลาดพร้าว"
    },
    {
      "name": "ถนนรัชดาภิเษก",
      "description": "ศาลอาญา"
    },
    {
      "name": "ถนนเทศบาลสงเคราะห์",
      "description": "ตลาดประชานิเวศน์ ขาเข้า"
    },
    {
      "name": "ถนนเทศบาลสงเคราะห์",
      "description": "ตลาดประชานิเวศน์ ขาออก"
    },
    {
      "name": "ถนนเทศบาลสงเคราะห์",
      "description": "ปากซอยเสนานิคม 1-คลองลาดพร้าว"
    }
  ],
  "meanFloodLevel": 49.2,
  "meanFloodLevelMaximumPoint": {
    "value": 51.4,
    "year": 2565,
    "districtId": 5,
    "districtName": "จตุจักร"
  }
}